
{"items":[{"name":"GrpcRichError","href":"GrpcRichError.html","topicHref":"GrpcRichError.html","topicUid":"GrpcRichError","type":"Namespace","items":[{"name":"AnyListExtensions","href":"GrpcRichError.AnyListExtensions.html","topicHref":"GrpcRichError.AnyListExtensions.html","topicUid":"GrpcRichError.AnyListExtensions","type":"Class"},{"name":"MetadataExtensions","href":"GrpcRichError.MetadataExtensions.html","topicHref":"GrpcRichError.MetadataExtensions.html","topicUid":"GrpcRichError.MetadataExtensions","type":"Class"},{"name":"RpcExceptionExtensions","href":"GrpcRichError.RpcExceptionExtensions.html","topicHref":"GrpcRichError.RpcExceptionExtensions.html","topicUid":"GrpcRichError.RpcExceptionExtensions","type":"Class"},{"name":"StatusExtensions","href":"GrpcRichError.StatusExtensions.html","topicHref":"GrpcRichError.StatusExtensions.html","topicUid":"GrpcRichError.StatusExtensions","type":"Class"}]}],"memberLayout":"SamePage"}
